tilearn/llm.cpython-310-x86_64-linux-gnu.so
"tilearn/llm/quant/algorithm/LayerwiseSearchSmoothQuant/models/modeling_py_patch/mixtral/configs/E=16,N=2688,device_name=NVIDIA_H100_80GB_HBM3.json"
"tilearn/llm/quant/algorithm/LayerwiseSearchSmoothQuant/models/modeling_py_patch/mixtral/configs/E=8,N=2048,device_name=NVIDIA_A100-SXM4-80GB.json"
tilearn/llm/quant/algorithm/LayerwiseSearchSmoothQuant/models/modeling_py_patch/mixtral/configs/README
"tilearn/llm/quant/algorithm/LayerwiseSearchSmoothQuant/models/modeling_py_patch/mixtral/configs/E=8,N=7168,device_name=NVIDIA_H100_80GB_HBM3.json"
"tilearn/llm/quant/algorithm/LayerwiseSearchSmoothQuant/models/modeling_py_patch/mixtral/configs/E=8,N=1792,device_name=NVIDIA_A100-SXM4-40GB.json"
"tilearn/llm/quant/algorithm/LayerwiseSearchSmoothQuant/models/modeling_py_patch/mixtral/configs/E=8,N=3584,device_name=NVIDIA_A100-SXM4-40GB.json"
"tilearn/llm/quant/algorithm/LayerwiseSearchSmoothQuant/models/modeling_py_patch/mixtral/configs/E=8,N=3584,device_name=NVIDIA_H100_80GB_HBM3.json"
"tilearn/llm/quant/algorithm/LayerwiseSearchSmoothQuant/models/modeling_py_patch/mixtral/configs/E=16,N=1344,device_name=NVIDIA_A100-SXM4-40GB.json"
"tilearn/llm/quant/algorithm/LayerwiseSearchSmoothQuant/models/modeling_py_patch/mixtral/configs/E=8,N=2048,device_name=NVIDIA_H100_80GB_HBM3.json"
"tilearn/llm/quant/algorithm/LayerwiseSearchSmoothQuant/models/modeling_py_patch/mixtral/configs/E=8,N=1792,device_name=NVIDIA_A100-SXM4-80GB.json"
"tilearn/llm/quant/algorithm/LayerwiseSearchSmoothQuant/models/modeling_py_patch/mixtral/configs/E=8,N=7168,device_name=NVIDIA_H100_80GB_HBM3,dtype=float8.json"
"tilearn/llm/quant/algorithm/LayerwiseSearchSmoothQuant/models/modeling_py_patch/mixtral/configs/E=16,N=1344,device_name=NVIDIA_H100_80GB_HBM3.json"
"tilearn/llm/quant/algorithm/LayerwiseSearchSmoothQuant/models/modeling_py_patch/mixtral/configs/E=8,N=7168,device_name=NVIDIA_A100-SXM4-80GB.json"
tilearn_llm-1.1.0.dist-info/WHEEL
tilearn_llm-1.1.0.dist-info/METADATA
tilearn_llm-1.1.0.dist-info/top_level.txt
tilearn_llm-1.1.0.dist-info/entry_points.txt
tilearn_llm-1.1.0.dist-info/RECORD
