Metadata-Version: 2.1
Name: tilearn-llm
Version: 1.1.0
Summary: TILEARN for LLM
Author-email: Bo Yang <boyyang@tencent.com>, Boyuan Deng <bryandeng@tencent.com>, Chenyang Guo <chenyangguo@tencent.com>, Run Li <danerli@tencent.com>, Yahui Chen <huecheng@tencent.com>, Jing Gong <jennygong@tencent.com>, Minhao Qin <lemonqin@tencent.com>
License: Copyright (c) 2023 - 2025 TENCENT CORPORATION. All rights reserved.
Project-URL: Homepage, https://cloud.tencent.com/document/product/1511/64787
Keywords: pytorch,LLM
Classifier: Programming Language :: Python :: 3 :: Only
Classifier: Programming Language :: Python :: 3.8
Classifier: Programming Language :: Python :: 3.9
Classifier: Programming Language :: Python :: 3.10
Classifier: Programming Language :: Python :: 3.11
Classifier: Programming Language :: Python :: 3.12
Requires-Python: >=3.8
Requires-Dist: cryptography
Requires-Dist: easydict
Requires-Dist: transformers
Provides-Extra: test
Requires-Dist: pytest >=6 ; extra == 'test'
